planet/__init__.py
planet/__version__.py
planet/auth.py
planet/auth_builtins.py
planet/constants.py
planet/data_filter.py
planet/exceptions.py
planet/geojson.py
planet/http.py
planet/io.py
planet/models.py
planet/order_request.py
planet/reporting.py
planet/specs.py
planet/subscription_request.py
planet/cli/__init__.py
planet/cli/auth.py
planet/cli/cli.py
planet/cli/cmds.py
planet/cli/collect.py
planet/cli/data.py
planet/cli/destinations.py
planet/cli/features.py
planet/cli/io.py
planet/cli/mosaics.py
planet/cli/options.py
planet/cli/orders.py
planet/cli/session.py
planet/cli/subscriptions.py
planet/cli/types.py
planet/cli/validators.py
planet/clients/__init__.py
planet/clients/base.py
planet/clients/data.py
planet/clients/destinations.py
planet/clients/features.py
planet/clients/mosaics.py
planet/clients/orders.py
planet/clients/subscriptions.py
planet/data/Feature.json
planet/data/README.md
planet/sync/__init__.py
planet/sync/client.py
planet/sync/data.py
planet/sync/destinations.py
planet/sync/features.py
planet/sync/mosaics.py
planet/sync/orders.py
planet/sync/subscriptions.py
planet-3.1.2.dist-info/licenses/LICENSE
planet-3.1.2.dist-info/METADATA
planet-3.1.2.dist-info/WHEEL
planet-3.1.2.dist-info/entry_points.txt
planet-3.1.2.dist-info/top_level.txt
planet-3.1.2.dist-info/RECORD
