Metadata-Version: 2.4
Name: planet
Version: 3.1.2
Summary: Planet SDK for Python
Author-email: Planet <python-sdk-contributors@planet.com>
License: Apache License
Project-URL: Repository, https://github.com/planetlabs/planet-client-python
Keywords: planet,api,sdk,client
Classifier: Development Status :: 5 - Production/Stable
Classifier: Environment :: Console
Classifier: Intended Audience :: Developers
Classifier: License :: OSI Approved :: Apache Software License
Classifier: Operating System :: OS Independent
Classifier: Programming Language :: Python :: 3
Classifier: Topic :: Scientific/Engineering
Classifier: Topic :: Software Development
Classifier: Topic :: Utilities
Requires-Python: >=3.10
License-File: LICENSE
Requires-Dist: click!=8.2.1,>=8.0
Requires-Dist: geojson
Requires-Dist: httpx>=0.28.0
Requires-Dist: jsonschema
Requires-Dist: pyjwt>=2.1
Requires-Dist: tqdm>=4.56
Requires-Dist: typing-extensions
Requires-Dist: planet-auth>=2.1.0
Provides-Extra: test
Requires-Dist: pytest==8.3.3; extra == "test"
Requires-Dist: anyio; extra == "test"
Requires-Dist: pytest-cov; extra == "test"
Requires-Dist: respx>=0.22.0; extra == "test"
Requires-Dist: coverage[toml]; extra == "test"
Provides-Extra: lint
Requires-Dist: flake8; extra == "lint"
Requires-Dist: mypy; extra == "lint"
Requires-Dist: yapf==0.43.0; extra == "lint"
Provides-Extra: docs
Requires-Dist: mkdocs==1.4.2; extra == "docs"
Requires-Dist: mkdocs-click==0.7.0; extra == "docs"
Requires-Dist: mkdocs-material==8.2.11; extra == "docs"
Requires-Dist: mkdocstrings==0.18.1; extra == "docs"
Requires-Dist: mkdocs_autorefs==1.0.1; extra == "docs"
Requires-Dist: mkdocs-macros-plugin==1.3.7; extra == "docs"
Provides-Extra: dev
Requires-Dist: planet[docs,lint,test]; extra == "dev"
Dynamic: license-file
